portiapy/VERSION
portiapy/__init__.py
portiapy/axioms.py
portiapy/describe.py
portiapy/events.py
portiapy/phases.py
portiapy/portia.py
portiapy/profile.py
portiapy/select.py
portiapy/specs.py
portiapy/summary.py
portiapy/utils.py
portiapy/version.py
portiapy-1.2.4.dist-info/LICENSE
portiapy-1.2.4.dist-info/METADATA
portiapy-1.2.4.dist-info/WHEEL
portiapy-1.2.4.dist-info/top_level.txt
portiapy-1.2.4.dist-info/RECORD
