Metadata-Version: 2.1
Name: portiapy
Version: 1.2.4
Summary: A small package for handling Agriness Edge's REST API
Home-page: https://github.com/AgrinessEdgeIoT/portiapy
Author: Matheus Mota, Lucas Góes
Author-email: matheus@agrinessedge.com, lucas@agrinessedge.com
Classifier: Programming Language :: Python :: 3
Classifier: License :: OSI Approved :: MIT License
Classifier: Operating System :: OS Independent
License-File: LICENSE
Requires-Dist: arrow (>=1.2.3)
Requires-Dist: pandas (>=1.5.3)
Requires-Dist: plotly (>=5.13.1)
Requires-Dist: python-dateutil (>=2.8.2)
Requires-Dist: python-dotenv (>=1.0.0)
Requires-Dist: pytz (>=2022.7.1)
Requires-Dist: requests (>=2.28.2)
